TejToolAPI/Map_Dask_API.py
TejToolAPI/TejToolAPI.py
TejToolAPI/__init__.py
TejToolAPI/_version.py
TejToolAPI/exchange_calendar.py
TejToolAPI/meta_types.py
TejToolAPI/parameters.py
TejToolAPI/utils.py
TejToolAPI/tables/all_meta.json
TejToolAPI/tables/columns_group.xlsx
TejToolAPI/tables/~$columns_group.xlsx
tej_tool_api-1.2.11.dist-info/licenses/LICENSE
tej_tool_api-1.2.11.dist-info/METADATA
tej_tool_api-1.2.11.dist-info/WHEEL
tej_tool_api-1.2.11.dist-info/top_level.txt
tej_tool_api-1.2.11.dist-info/RECORD
