Metadata-Version: 2.4
Name: tej-tool-api
Version: 1.2.11
Summary: Package to fetch a large quantity of data from tejapi.
Author: tej
Author-email: tej@tej.com.tw
Maintainer: tej api Development Team
Maintainer-email: tej@tej.com.tw
License: Apache-2.0
Project-URL: homepage, https://api.tej.com.tw
Project-URL: repository, https://github.com/tejtw/TEJ_TOOL_API
Classifier: Development Status :: 4 - Beta
Classifier: Natural Language :: English
Classifier: Natural Language :: Chinese (Traditional)
Classifier: Programming Language :: Python
Classifier: Topic :: Office/Business :: Financial :: Investment
Classifier: Topic :: Scientific/Engineering :: Information Analysis
Requires-Python: >=3.8
License-File: LICENSE
Requires-Dist: dask>=2024.9.0
Requires-Dist: distributed>=2024.9.0
Requires-Dist: dask-expr>=1.1.15
Requires-Dist: pandas>=2.0.0
Requires-Dist: tejapi>=0.1.27
Requires-Dist: xlrd>=1.0.0
Requires-Dist: openpyxl
Requires-Dist: fastparquet
Requires-Dist: pyarrow
Dynamic: license-file
